{"resource": "playerdashptpass", "parameters": {"PerMode": "Totals", "LeagueID": "00", "Season": "2015-16", "SeasonType": "Regular Season", "PlayerID": 201950, "TeamID": 0, "Outcome": null, "Location": null, "Month": 0, "SeasonSegment": null, "DateFrom": null, "DateTo": null, "OpponentTeamID": 0, "VsConference": null, "VsDivision": null, "LastNGames": 0, "ISTRound": null}, "resultSets": [{"name": "PassesMade", "headers": ["PLAYER_ID", "PLAYER_NAME_LAST_FIRST", "TEAM_NAME", "TEAM_ID", "TEAM_ABBREVIATION", "PASS_TYPE", "G", "PASS_TO", "PASS_TEAMMATE_PLAYER_ID", "FREQUENCY", "PASS", "AST", "FGM", "FGA", "FG_PCT", "FG2M", "FG2A", "FG2_PCT", "FG3M", "FG3A", "FG3_PCT"], "rowSet": [[201950, "Holiday, Jrue", "New Orleans Pelicans", 1610612740, "NOP", "made", 65, "Dejean-Jones, Bryce", 1626214, 0.012, 35, 6, 11, 20, 0.55, 7, 12, 0.583, 4, 8, 0.5], [201950, "Holiday, Jrue", "New Orleans Pelicans", 1610612740, "NOP", "made", 65, "Frazier, Tim", 204025, 0.01, 31, 1, 5, 8, 0.625, 3, 5, 0.6, 2, 3, 0.667], [201950, "Holiday, Jrue", "New Orleans Pelicans", 1610612740, "NOP", "made", 65, "Johnson, Orlando", 203111, 0.003, 10, 1, 1, 3, 0.333, 1, 2, 0.5, 0, 1, 0.0], [201950, "Holiday, Jrue", "New Orleans Pelicans", 1610612740, "NOP", "made", 65, "Davis, Anthony", 203076, 0.223, 671, 128, 158, 330, 0.479, 148, 298, 0.497, 10, 32, 0.313], [201950, "Holiday, Jrue", "New Orleans Pelicans", 1610612740, "NOP", "made", 65, "Cole, Norris", 202708, 0.103, 311, 20, 38, 93, 0.409, 29, 69, 0.42, 9, 24, 0.375], [201950, "Holiday, Jrue", "New Orleans Pelicans", 1610612740, "NOP", "made", 65, "Hamilton, Jordan", 202706, 0.001, 3, 1, 1, 2, 0.5, 0, 0, 0.0, 1, 2, 0.5], [201950, "Holiday, Jrue", "New Orleans Pelicans", 1610612740, "NOP", "made", 65, "Smith, Ish", 202397, 0.012, 35, 0, 1, 3, 0.333, 1, 2, 0.5, 0, 1, 0.0], [201950, "Holiday, Jrue", "New Orleans Pelicans", 1610612740, "NOP", "made", 65, "Babbitt, Luke", 202337, 0.033, 100, 13, 17, 41, 0.415, 10, 23, 0.435, 7, 18, 0.389], [201950, "Holiday, Jrue", "New Orleans Pelicans", 1610612740, "NOP", "made", 65, "Gee, Alonzo", 202087, 0.052, 157, 19, 21, 45, 0.467, 19, 35, 0.543, 2, 10, 0.2], [201950, "Holiday, Jrue", "New Orleans Pelicans", 1610612740, "NOP", "made", 65, "Cunningham, Dante", 201967, 0.071, 213, 36, 38, 82, 0.463, 25, 41, 0.61, 13, 41, 0.317], [201950, "Holiday, Jrue", "New Orleans Pelicans", 1610612740, "NOP", "made", 65, "Douglas, Toney", 201962, 0.086, 258, 15, 20, 64, 0.313, 8, 34, 0.235, 12, 30, 0.4], [201950, "Holiday, Jrue", "New Orleans Pelicans", 1610612740, "NOP", "made", 65, "Holiday, Jrue", 201950, 0.0, 1, 0, 0, 0, 0.0, 0, 0, 0.0, 0, 0, 0.0], [201950, "Holiday, Jrue", "New Orleans Pelicans", 1610612740, "NOP", "made", 65, "Evans, Tyreke", 201936, 0.052, 157, 8, 15, 35, 0.429, 8, 20, 0.4, 7, 15, 0.467], [201950, "Holiday, Jrue", "New Orleans Pelicans", 1610612740, "NOP", "made", 65, "Asik, Omer", 201600, 0.034, 102, 11, 11, 24, 0.458, 11, 24, 0.458, 0, 0, 0.0], [201950, "Holiday, Jrue", "New Orleans Pelicans", 1610612740, "NOP", "made", 65, "Anderson, Ryan", 201583, 0.167, 503, 67, 87, 247, 0.352, 52, 142, 0.366, 35, 105, 0.333], [201950, "Holiday, Jrue", "New Orleans Pelicans", 1610612740, "NOP", "made", 65, "Ajinca, Alexis", 201582, 0.036, 108, 21, 24, 59, 0.407, 24, 59, 0.407, 0, 0, 0.0], [201950, "Holiday, Jrue", "New Orleans Pelicans", 1610612740, "NOP", "made", 65, "Gordon, Eric", 201569, 0.086, 260, 30, 38, 105, 0.362, 15, 43, 0.349, 23, 62, 0.371], [201950, "Holiday, Jrue", "New Orleans Pelicans", 1610612740, "NOP", "made", 65, "Perkins, Kendrick", 2570, 0.017, 51, 7, 7, 13, 0.538, 7, 13, 0.538, 0, 0, 0.0]]}, {"name": "PassesReceived", "headers": ["PLAYER_ID", "PLAYER_NAME_LAST_FIRST", "TEAM_NAME", "TEAM_ID", "TEAM_ABBREVIATION", "PASS_TYPE", "G", "PASS_FROM", "PASS_TEAMMATE_PLAYER_ID", "FREQUENCY", "PASS", "AST", "FGM", "FGA", "FG_PCT", "FG2M", "FG2A", "FG2_PCT", "FG3M", "FG3A", "FG3_PCT"], "rowSet": [[201950, "Holiday, Jrue", "New Orleans Pelicans", 1610612740, "NOP", "received", 65, "Dejean-Jones, Bryce", 1626214, 0.009, 35, 0, 4, 13, 0.308, 4, 11, 0.364, 0, 2, 0.0], [201950, "Holiday, Jrue", "New Orleans Pelicans", 1610612740, "NOP", "received", 65, "Frazier, Tim", 204025, 0.01, 36, 2, 3, 8, 0.375, 1, 6, 0.167, 2, 2, 1.0], [201950, "Holiday, Jrue", "New Orleans Pelicans", 1610612740, "NOP", "received", 65, "Johnson, Orlando", 203111, 0.003, 12, 0, 3, 4, 0.75, 2, 3, 0.667, 1, 1, 1.0], [201950, "Holiday, Jrue", "New Orleans Pelicans", 1610612740, "NOP", "received", 65, "Davis, Anthony", 203076, 0.195, 731, 17, 61, 150, 0.407, 45, 108, 0.417, 16, 42, 0.381], [201950, "Holiday, Jrue", "New Orleans Pelicans", 1610612740, "NOP", "received", 65, "Cole, Norris", 202708, 0.111, 414, 20, 53, 126, 0.421, 39, 95, 0.411, 14, 31, 0.452], [201950, "Holiday, Jrue", "New Orleans Pelicans", 1610612740, "NOP", "received", 65, "Hamilton, Jordan", 202706, 0.001, 2, 0, 1, 1, 1.0, 1, 1, 1.0, 0, 0, 0.0], [201950, "Holiday, Jrue", "New Orleans Pelicans", 1610612740, "NOP", "received", 65, "Smith, Ish", 202397, 0.018, 68, 4, 7, 23, 0.304, 5, 16, 0.313, 2, 7, 0.286], [201950, "Holiday, Jrue", "New Orleans Pelicans", 1610612740, "NOP", "received", 65, "Babbitt, Luke", 202337, 0.036, 136, 2, 6, 33, 0.182, 5, 21, 0.238, 1, 12, 0.083], [201950, "Holiday, Jrue", "New Orleans Pelicans", 1610612740, "NOP", "received", 65, "Gee, Alonzo", 202087, 0.064, 239, 4, 22, 53, 0.415, 19, 40, 0.475, 3, 13, 0.231], [201950, "Holiday, Jrue", "New Orleans Pelicans", 1610612740, "NOP", "received", 65, "Cunningham, Dante", 201967, 0.085, 320, 7, 33, 85, 0.388, 29, 70, 0.414, 4, 15, 0.267], [201950, "Holiday, Jrue", "New Orleans Pelicans", 1610612740, "NOP", "received", 65, "Douglas, Toney", 201962, 0.088, 330, 17, 47, 100, 0.47, 37, 70, 0.529, 10, 30, 0.333], [201950, "Holiday, Jrue", "New Orleans Pelicans", 1610612740, "NOP", "received", 65, "Holiday, Jrue", 201950, 0.0, 1, 0, 0, 0, 0.0, 0, 0, 0.0, 0, 0, 0.0], [201950, "Holiday, Jrue", "New Orleans Pelicans", 1610612740, "NOP", "received", 65, "Evans, Tyreke", 201936, 0.053, 197, 14, 29, 63, 0.46, 20, 44, 0.455, 9, 19, 0.474], [201950, "Holiday, Jrue", "New Orleans Pelicans", 1610612740, "NOP", "received", 65, "Asik, Omer", 201600, 0.073, 272, 3, 17, 52, 0.327, 11, 37, 0.297, 6, 15, 0.4], [201950, "Holiday, Jrue", "New Orleans Pelicans", 1610612740, "NOP", "received", 65, "Anderson, Ryan", 201583, 0.128, 480, 14, 55, 114, 0.482, 46, 87, 0.529, 9, 27, 0.333], [201950, "Holiday, Jrue", "New Orleans Pelicans", 1610612740, "NOP", "received", 65, "Ajinca, Alexis", 201582, 0.052, 194, 2, 15, 44, 0.341, 12, 36, 0.333, 3, 8, 0.375], [201950, "Holiday, Jrue", "New Orleans Pelicans", 1610612740, "NOP", "received", 65, "Gordon, Eric", 201569, 0.039, 146, 3, 8, 26, 0.308, 8, 18, 0.444, 0, 8, 0.0], [201950, "Holiday, Jrue", "New Orleans Pelicans", 1610612740, "NOP", "received", 65, "Perkins, Kendrick", 2570, 0.035, 131, 1, 11, 33, 0.333, 10, 22, 0.455, 1, 11, 0.091]]}]}