{"resource": "playerdashptpass", "parameters": {"PerMode": "Totals", "LeagueID": "00", "Season": "2015-16", "SeasonType": "Regular Season", "PlayerID": 203476, "TeamID": 0, "Outcome": null, "Location": null, "Month": 0, "SeasonSegment": null, "DateFrom": null, "DateTo": null, "OpponentTeamID": 0, "VsConference": null, "VsDivision": null, "LastNGames": 0, "ISTRound": null}, "resultSets": [{"name": "PassesMade", "headers": ["PLAYER_ID", "PLAYER_NAME_LAST_FIRST", "TEAM_NAME", "TEAM_ID", "TEAM_ABBREVIATION", "PASS_TYPE", "G", "PASS_TO", "PASS_TEAMMATE_PLAYER_ID", "FREQUENCY", "PASS", "AST", "FGM", "FGA", "FG_PCT", "FG2M", "FG2A", "FG2_PCT", "FG3M", "FG3A", "FG3_PCT"], "rowSet": [[203476, "Dieng, Gorgui", "Minnesota Timberwolves", 1610612750, "MIN", "made", 82, "Towns, Karl-Anthony", 1626157, 0.041, 96, 24, 30, 50, 0.6, 29, 47, 0.617, 1, 3, 0.333], [203476, "Dieng, Gorgui", "Minnesota Timberwolves", 1610612750, "MIN", "made", 82, "Jones, Tyus", 1626145, 0.052, 120, 3, 4, 10, 0.4, 2, 7, 0.286, 2, 3, 0.667], [203476, "Dieng, Gorgui", "Minnesota Timberwolves", 1610612750, "MIN", "made", 82, "Rudez, Damjan", 204014, 0.005, 11, 2, 2, 3, 0.667, 1, 2, 0.5, 1, 1, 1.0], [203476, "Dieng, Gorgui", "Minnesota Timberwolves", 1610612750, "MIN", "made", 82, "Wiggins, Andrew", 203952, 0.084, 194, 25, 39, 88, 0.443, 31, 71, 0.437, 8, 17, 0.471], [203476, "Dieng, Gorgui", "Minnesota Timberwolves", 1610612750, "MIN", "made", 82, "Payne, Adreian", 203940, 0.008, 18, 2, 3, 8, 0.375, 2, 7, 0.286, 1, 1, 1.0], [203476, "Dieng, Gorgui", "Minnesota Timberwolves", 1610612750, "MIN", "made", 82, "LaVine, Zach", 203897, 0.236, 547, 29, 51, 152, 0.336, 33, 103, 0.32, 18, 49, 0.367], [203476, "Dieng, Gorgui", "Minnesota Timberwolves", 1610612750, "MIN", "made", 82, "Muhammad, Shabazz", 203498, 0.053, 124, 28, 36, 64, 0.563, 30, 53, 0.566, 6, 11, 0.545], [203476, "Dieng, Gorgui", "Minnesota Timberwolves", 1610612750, "MIN", "made", 82, "Dieng, Gorgui", 203476, 0.0, 1, 0, 0, 0, 0.0, 0, 0, 0.0, 0, 0, 0.0], [203476, "Dieng, Gorgui", "Minnesota Timberwolves", 1610612750, "MIN", "made", 82, "Bjelica, Nemanja", 202357, 0.022, 52, 2, 3, 7, 0.429, 3, 4, 0.75, 0, 3, 0.0], [203476, "Dieng, Gorgui", "Minnesota Timberwolves", 1610612750, "MIN", "made", 82, "Rubio, Ricky", 201937, 0.399, 925, 12, 29, 80, 0.363, 19, 59, 0.322, 10, 21, 0.476], [203476, "Dieng, Gorgui", "Minnesota Timberwolves", 1610612750, "MIN", "made", 82, "Pekovic, Nikola", 201593, 0.001, 3, 1, 1, 3, 0.333, 1, 3, 0.333, 0, 0, 0.0], [203476, "Dieng, Gorgui", "Minnesota Timberwolves", 1610612750, "MIN", "made", 82, "Martin, Kevin", 2755, 0.029, 67, 4, 10, 31, 0.323, 7, 23, 0.304, 3, 8, 0.375], [203476, "Dieng, Gorgui", "Minnesota Timberwolves", 1610612750, "MIN", "made", 82, "Prince, Tayshaun", 2419, 0.028, 65, 5, 6, 17, 0.353, 6, 17, 0.353, 0, 0, 0.0], [203476, "Dieng, Gorgui", "Minnesota Timberwolves", 1610612750, "MIN", "made", 82, "Miller, Andre", 1889, 0.04, 94, 5, 9, 12, 0.75, 8, 10, 0.8, 1, 2, 0.5], [203476, "Dieng, Gorgui", "Minnesota Timberwolves", 1610612750, "MIN", "made", 82, "Garnett, Kevin", 708, 0.002, 4, 0, 0, 1, 0.0, 0, 1, 0.0, 0, 0, 0.0]]}, {"name": "PassesReceived", "headers": ["PLAYER_ID", "PLAYER_NAME_LAST_FIRST", "TEAM_NAME", "TEAM_ID", "TEAM_ABBREVIATION", "PASS_TYPE", "G", "PASS_FROM", "PASS_TEAMMATE_PLAYER_ID", "FREQUENCY", "PASS", "AST", "FGM", "FGA", "FG_PCT", "FG2M", "FG2A", "FG2_PCT", "FG3M", "FG3A", "FG3_PCT"], "rowSet": [[203476, "Dieng, Gorgui", "Minnesota Timberwolves", 1610612750, "MIN", "received", 82, "Towns, Karl-Anthony", 1626157, 0.087, 158, 25, 34, 65, 0.523, 34, 63, 0.54, 0, 2, 0.0], [203476, "Dieng, Gorgui", "Minnesota Timberwolves", 1610612750, "MIN", "received", 82, "Jones, Tyus", 1626145, 0.055, 100, 12, 13, 28, 0.464, 12, 25, 0.48, 1, 3, 0.333], [203476, "Dieng, Gorgui", "Minnesota Timberwolves", 1610612750, "MIN", "received", 82, "Rudez, Damjan", 204014, 0.006, 11, 2, 2, 5, 0.4, 2, 5, 0.4, 0, 0, 0.0], [203476, "Dieng, Gorgui", "Minnesota Timberwolves", 1610612750, "MIN", "received", 82, "Wiggins, Andrew", 203952, 0.11, 201, 18, 29, 56, 0.518, 26, 50, 0.52, 3, 6, 0.5], [203476, "Dieng, Gorgui", "Minnesota Timberwolves", 1610612750, "MIN", "received", 82, "Payne, Adreian", 203940, 0.016, 29, 3, 4, 7, 0.571, 4, 7, 0.571, 0, 0, 0.0], [203476, "Dieng, Gorgui", "Minnesota Timberwolves", 1610612750, "MIN", "received", 82, "LaVine, Zach", 203897, 0.256, 468, 49, 59, 130, 0.454, 59, 127, 0.465, 0, 3, 0.0], [203476, "Dieng, Gorgui", "Minnesota Timberwolves", 1610612750, "MIN", "received", 82, "Muhammad, Shabazz", 203498, 0.043, 79, 8, 12, 29, 0.414, 11, 27, 0.407, 1, 2, 0.5], [203476, "Dieng, Gorgui", "Minnesota Timberwolves", 1610612750, "MIN", "received", 82, "Dieng, Gorgui", 203476, 0.001, 1, 0, 0, 0, 0.0, 0, 0, 0.0, 0, 0, 0.0], [203476, "Dieng, Gorgui", "Minnesota Timberwolves", 1610612750, "MIN", "received", 82, "Smith, Greg", 202962, 0.001, 2, 0, 0, 1, 0.0, 0, 0, 0.0, 0, 1, 0.0], [203476, "Dieng, Gorgui", "Minnesota Timberwolves", 1610612750, "MIN", "received", 82, "Bjelica, Nemanja", 202357, 0.049, 90, 8, 9, 32, 0.281, 9, 32, 0.281, 0, 0, 0.0], [203476, "Dieng, Gorgui", "Minnesota Timberwolves", 1610612750, "MIN", "received", 82, "Rubio, Ricky", 201937, 0.276, 503, 74, 86, 188, 0.457, 85, 185, 0.459, 1, 3, 0.333], [203476, "Dieng, Gorgui", "Minnesota Timberwolves", 1610612750, "MIN", "received", 82, "Pekovic, Nikola", 201593, 0.001, 2, 0, 0, 1, 0.0, 0, 1, 0.0, 0, 0, 0.0], [203476, "Dieng, Gorgui", "Minnesota Timberwolves", 1610612750, "MIN", "received", 82, "Martin, Kevin", 2755, 0.034, 62, 6, 7, 21, 0.333, 7, 21, 0.333, 0, 0, 0.0], [203476, "Dieng, Gorgui", "Minnesota Timberwolves", 1610612750, "MIN", "received", 82, "Prince, Tayshaun", 2419, 0.028, 51, 4, 5, 15, 0.333, 5, 15, 0.333, 0, 0, 0.0], [203476, "Dieng, Gorgui", "Minnesota Timberwolves", 1610612750, "MIN", "received", 82, "Miller, Andre", 1889, 0.035, 64, 10, 13, 21, 0.619, 13, 21, 0.619, 0, 0, 0.0], [203476, "Dieng, Gorgui", "Minnesota Timberwolves", 1610612750, "MIN", "received", 82, "Garnett, Kevin", 708, 0.002, 4, 0, 0, 0, 0.0, 0, 0, 0.0, 0, 0, 0.0]]}]}