{"resource": "playerdashptpass", "parameters": {"PerMode": "Totals", "LeagueID": "00", "Season": "2023-24", "SeasonType": "Regular Season", "PlayerID": 1630346, "TeamID": 0, "Outcome": null, "Location": null, "Month": 0, "SeasonSegment": null, "DateFrom": null, "DateTo": null, "OpponentTeamID": 0, "VsConference": null, "VsDivision": null, "LastNGames": 0, "ISTRound": null}, "resultSets": [{"name": "PassesMade", "headers": ["PLAYER_ID", "PLAYER_NAME_LAST_FIRST", "TEAM_NAME", "TEAM_ID", "TEAM_ABBREVIATION", "PASS_TYPE", "G", "PASS_TO", "PASS_TEAMMATE_PLAYER_ID", "FREQUENCY", "PASS", "AST", "FGM", "FGA", "FG_PCT", "FG2M", "FG2A", "FG2_PCT", "FG3M", "FG3A", "FG3_PCT"], "rowSet": [[1630346, "Ryan, Matt", "New Orleans Pelicans", 1610612740, "NOP", "made", 26, "Hawkins, Jordan", 1641722, 0.099, 32, 0, 0, 7, 0.0, 0, 3, 0.0, 0, 4, 0.0], [1630346, "Ryan, Matt", "New Orleans Pelicans", 1610612740, "NOP", "made", 26, "Seabron, Dereon", 1631220, 0.012, 4, 0, 0, 0, 0.0, 0, 0, 0.0, 0, 0, 0.0], [1630346, "Ryan, Matt", "New Orleans Pelicans", 1610612740, "NOP", "made", 26, "Brockington, Izaiah", 1631167, 0.009, 3, 1, 1, 3, 0.333, 1, 2, 0.5, 0, 1, 0.0], [1630346, "Ryan, Matt", "New Orleans Pelicans", 1610612740, "NOP", "made", 26, "Daniels, Dyson", 1630700, 0.14, 45, 3, 4, 7, 0.571, 2, 3, 0.667, 2, 4, 0.5], [1630346, "Ryan, Matt", "New Orleans Pelicans", 1610612740, "NOP", "made", 26, "Alvarado, Jose", 1630631, 0.031, 10, 0, 0, 0, 0.0, 0, 0, 0.0, 0, 0, 0.0], [1630346, "Ryan, Matt", "New Orleans Pelicans", 1610612740, "NOP", "made", 26, "Crutcher, Jalen", 1630622, 0.003, 1, 0, 0, 0, 0.0, 0, 0, 0.0, 0, 0, 0.0], [1630346, "Ryan, Matt", "New Orleans Pelicans", 1610612740, "NOP", "made", 26, "Liddell, E.J.", 1630604, 0.006, 2, 0, 0, 1, 0.0, 0, 0, 0.0, 0, 1, 0.0], [1630346, "Ryan, Matt", "New Orleans Pelicans", 1610612740, "NOP", "made", 26, "Jones, Herbert", 1630529, 0.081, 26, 1, 2, 4, 0.5, 1, 3, 0.333, 1, 1, 1.0], [1630346, "Ryan, Matt", "New Orleans Pelicans", 1610612740, "NOP", "made", 26, "Robinson-Earl, Jeremiah", 1630526, 0.034, 11, 4, 4, 5, 0.8, 3, 4, 0.75, 1, 1, 1.0], [1630346, "Ryan, Matt", "New Orleans Pelicans", 1610612740, "NOP", "made", 26, "Marshall, Naji", 1630230, 0.071, 23, 0, 1, 4, 0.25, 1, 2, 0.5, 0, 2, 0.0], [1630346, "Ryan, Matt", "New Orleans Pelicans", 1610612740, "NOP", "made", 26, "Lewis Jr., Kira", 1630184, 0.056, 18, 1, 1, 3, 0.333, 1, 1, 1.0, 0, 2, 0.0], [1630346, "Ryan, Matt", "New Orleans Pelicans", 1610612740, "NOP", "made", 26, "Williamson, Zion", 1629627, 0.081, 26, 2, 5, 9, 0.556, 5, 9, 0.556, 0, 0, 0.0], [1630346, "Ryan, Matt", "New Orleans Pelicans", 1610612740, "NOP", "made", 26, "Gates, Kaiser", 1629232, 0.003, 1, 0, 0, 1, 0.0, 0, 0, 0.0, 0, 1, 0.0], [1630346, "Ryan, Matt", "New Orleans Pelicans", 1610612740, "NOP", "made", 26, "Ingram, Brandon", 1627742, 0.09, 29, 1, 3, 7, 0.429, 3, 6, 0.5, 0, 1, 0.0], [1630346, "Ryan, Matt", "New Orleans Pelicans", 1610612740, "NOP", "made", 26, "Nance Jr., Larry", 1626204, 0.047, 15, 1, 1, 2, 0.5, 0, 1, 0.0, 1, 1, 1.0], [1630346, "Ryan, Matt", "New Orleans Pelicans", 1610612740, "NOP", "made", 26, "Zeller, Cody", 203469, 0.037, 12, 0, 0, 1, 0.0, 0, 1, 0.0, 0, 0, 0.0], [1630346, "Ryan, Matt", "New Orleans Pelicans", 1610612740, "NOP", "made", 26, "McCollum, CJ", 203468, 0.121, 39, 3, 8, 15, 0.533, 5, 9, 0.556, 3, 6, 0.5], [1630346, "Ryan, Matt", "New Orleans Pelicans", 1610612740, "NOP", "made", 26, "Valan\u010di\u016bnas, Jonas", 202685, 0.078, 25, 2, 3, 9, 0.333, 3, 9, 0.333, 0, 0, 0.0]]}, {"name": "PassesReceived", "headers": ["PLAYER_ID", "PLAYER_NAME_LAST_FIRST", "TEAM_NAME", "TEAM_ID", "TEAM_ABBREVIATION", "PASS_TYPE", "G", "PASS_FROM", "PASS_TEAMMATE_PLAYER_ID", "FREQUENCY", "PASS", "AST", "FGM", "FGA", "FG_PCT", "FG2M", "FG2A", "FG2_PCT", "FG3M", "FG3A", "FG3_PCT"], "rowSet": [[1630346, "Ryan, Matt", "New Orleans Pelicans", 1610612740, "NOP", "received", 26, "Hawkins, Jordan", 1641722, 0.087, 27, 3, 3, 7, 0.429, 0, 0, 0.0, 3, 7, 0.429], [1630346, "Ryan, Matt", "New Orleans Pelicans", 1610612740, "NOP", "received", 26, "Seabron, Dereon", 1631220, 0.032, 10, 1, 1, 3, 0.333, 0, 1, 0.0, 1, 2, 0.5], [1630346, "Ryan, Matt", "New Orleans Pelicans", 1610612740, "NOP", "received", 26, "Brockington, Izaiah", 1631167, 0.006, 2, 0, 0, 1, 0.0, 0, 0, 0.0, 0, 1, 0.0], [1630346, "Ryan, Matt", "New Orleans Pelicans", 1610612740, "NOP", "received", 26, "Daniels, Dyson", 1630700, 0.068, 21, 3, 3, 8, 0.375, 2, 3, 0.667, 1, 5, 0.2], [1630346, "Ryan, Matt", "New Orleans Pelicans", 1610612740, "NOP", "received", 26, "Alvarado, Jose", 1630631, 0.029, 9, 2, 2, 3, 0.667, 0, 0, 0.0, 2, 3, 0.667], [1630346, "Ryan, Matt", "New Orleans Pelicans", 1610612740, "NOP", "received", 26, "Liddell, E.J.", 1630604, 0.003, 1, 0, 0, 0, 0.0, 0, 0, 0.0, 0, 0, 0.0], [1630346, "Ryan, Matt", "New Orleans Pelicans", 1610612740, "NOP", "received", 26, "Murphy III, Trey", 1630530, 0.01, 3, 1, 1, 3, 0.333, 0, 0, 0.0, 1, 3, 0.333], [1630346, "Ryan, Matt", "New Orleans Pelicans", 1610612740, "NOP", "received", 26, "Jones, Herbert", 1630529, 0.084, 26, 3, 3, 7, 0.429, 0, 1, 0.0, 3, 6, 0.5], [1630346, "Ryan, Matt", "New Orleans Pelicans", 1610612740, "NOP", "received", 26, "Robinson-Earl, Jeremiah", 1630526, 0.042, 13, 0, 0, 3, 0.0, 0, 1, 0.0, 0, 2, 0.0], [1630346, "Ryan, Matt", "New Orleans Pelicans", 1610612740, "NOP", "received", 26, "Marshall, Naji", 1630230, 0.042, 13, 1, 1, 4, 0.25, 1, 1, 1.0, 0, 3, 0.0], [1630346, "Ryan, Matt", "New Orleans Pelicans", 1610612740, "NOP", "received", 26, "Lewis Jr., Kira", 1630184, 0.055, 17, 5, 6, 10, 0.6, 1, 3, 0.333, 5, 7, 0.714], [1630346, "Ryan, Matt", "New Orleans Pelicans", 1610612740, "NOP", "received", 26, "Williamson, Zion", 1629627, 0.126, 39, 8, 8, 20, 0.4, 2, 3, 0.667, 6, 17, 0.353], [1630346, "Ryan, Matt", "New Orleans Pelicans", 1610612740, "NOP", "received", 26, "Gates, Kaiser", 1629232, 0.003, 1, 0, 0, 0, 0.0, 0, 0, 0.0, 0, 0, 0.0], [1630346, "Ryan, Matt", "New Orleans Pelicans", 1610612740, "NOP", "received", 26, "Ingram, Brandon", 1627742, 0.087, 27, 5, 5, 14, 0.357, 0, 1, 0.0, 5, 13, 0.385], [1630346, "Ryan, Matt", "New Orleans Pelicans", 1610612740, "NOP", "received", 26, "Nance Jr., Larry", 1626204, 0.055, 17, 1, 1, 2, 0.5, 1, 1, 1.0, 0, 1, 0.0], [1630346, "Ryan, Matt", "New Orleans Pelicans", 1610612740, "NOP", "received", 26, "Zeller, Cody", 203469, 0.071, 22, 2, 2, 7, 0.286, 0, 3, 0.0, 2, 4, 0.5], [1630346, "Ryan, Matt", "New Orleans Pelicans", 1610612740, "NOP", "received", 26, "McCollum, CJ", 203468, 0.113, 35, 8, 8, 15, 0.533, 1, 4, 0.25, 7, 11, 0.636], [1630346, "Ryan, Matt", "New Orleans Pelicans", 1610612740, "NOP", "received", 26, "Valan\u010di\u016bnas, Jonas", 202685, 0.087, 27, 3, 3, 6, 0.5, 0, 2, 0.0, 3, 4, 0.75]]}]}