{"resource": "playerdashptpass", "parameters": {"PerMode": "Totals", "LeagueID": "00", "Season": "2023-24", "SeasonType": "Regular Season", "PlayerID": 1628392, "TeamID": 0, "Outcome": null, "Location": null, "Month": 0, "SeasonSegment": null, "DateFrom": null, "DateTo": null, "OpponentTeamID": 0, "VsConference": null, "VsDivision": null, "LastNGames": 0, "ISTRound": null}, "resultSets": [{"name": "PassesMade", "headers": ["PLAYER_ID", "PLAYER_NAME_LAST_FIRST", "TEAM_NAME", "TEAM_ID", "TEAM_ABBREVIATION", "PASS_TYPE", "G", "PASS_TO", "PASS_TEAMMATE_PLAYER_ID", "FREQUENCY", "PASS", "AST", "FGM", "FGA", "FG_PCT", "FG2M", "FG2A", "FG2_PCT", "FG3M", "FG3A", "FG3_PCT"], "rowSet": [[1628392, "Hartenstein, Isaiah", "New York Knicks", 1610612752, "NYK", "made", 75, "Toppin, Jacob", 1631210, 0.001, 2, 0, 0, 1, 0.0, 0, 0, 0.0, 0, 1, 0.0], [1628392, "Hartenstein, Isaiah", "New York Knicks", 1610612752, "NYK", "made", 75, "McBride, Miles", 1630540, 0.082, 207, 16, 19, 38, 0.5, 8, 15, 0.533, 11, 23, 0.478], [1628392, "Hartenstein, Isaiah", "New York Knicks", 1610612752, "NYK", "made", 75, "Flynn, Malachi", 1630201, 0.004, 9, 0, 0, 0, 0.0, 0, 0, 0.0, 0, 0, 0.0], [1628392, "Hartenstein, Isaiah", "New York Knicks", 1610612752, "NYK", "made", 75, "Quickley, Immanuel", 1630193, 0.074, 188, 8, 18, 45, 0.4, 10, 29, 0.345, 8, 16, 0.5], [1628392, "Hartenstein, Isaiah", "New York Knicks", 1610612752, "NYK", "made", 75, "Achiuwa, Precious", 1630173, 0.024, 60, 7, 9, 15, 0.6, 7, 12, 0.583, 2, 3, 0.667], [1628392, "Hartenstein, Isaiah", "New York Knicks", 1610612752, "NYK", "made", 75, "Grimes, Quentin", 1629656, 0.012, 30, 5, 6, 11, 0.545, 3, 5, 0.6, 3, 6, 0.5], [1628392, "Hartenstein, Isaiah", "New York Knicks", 1610612752, "NYK", "made", 75, "Barrett, RJ", 1629628, 0.026, 66, 7, 11, 31, 0.355, 8, 22, 0.364, 3, 9, 0.333], [1628392, "Hartenstein, Isaiah", "New York Knicks", 1610612752, "NYK", "made", 75, "Milton, Shake", 1629003, 0.001, 2, 0, 0, 0, 0.0, 0, 0, 0.0, 0, 0, 0.0], [1628392, "Hartenstein, Isaiah", "New York Knicks", 1610612752, "NYK", "made", 75, "DiVincenzo, Donte", 1628978, 0.135, 342, 42, 49, 116, 0.422, 22, 46, 0.478, 27, 70, 0.386], [1628392, "Hartenstein, Isaiah", "New York Knicks", 1610612752, "NYK", "made", 75, "Brunson, Jalen", 1628973, 0.37, 933, 34, 104, 243, 0.428, 86, 186, 0.462, 18, 57, 0.316], [1628392, "Hartenstein, Isaiah", "New York Knicks", 1610612752, "NYK", "made", 75, "Hart, Josh", 1628404, 0.141, 355, 29, 34, 78, 0.436, 28, 62, 0.452, 6, 16, 0.375], [1628392, "Hartenstein, Isaiah", "New York Knicks", 1610612752, "NYK", "made", 75, "Anunoby, OG", 1628384, 0.027, 69, 9, 11, 27, 0.407, 8, 17, 0.471, 3, 10, 0.3], [1628392, "Hartenstein, Isaiah", "New York Knicks", 1610612752, "NYK", "made", 75, "Randle, Julius", 203944, 0.075, 190, 17, 29, 73, 0.397, 23, 50, 0.46, 6, 23, 0.261], [1628392, "Hartenstein, Isaiah", "New York Knicks", 1610612752, "NYK", "made", 75, "Fournier, Evan", 203095, 0.001, 3, 1, 1, 2, 0.5, 0, 0, 0.0, 1, 2, 0.5], [1628392, "Hartenstein, Isaiah", "New York Knicks", 1610612752, "NYK", "made", 75, "Bogdanovic, Bojan", 202711, 0.019, 48, 10, 12, 21, 0.571, 11, 14, 0.786, 1, 7, 0.143], [1628392, "Hartenstein, Isaiah", "New York Knicks", 1610612752, "NYK", "made", 75, "Burks, Alec", 202692, 0.008, 21, 2, 2, 7, 0.286, 1, 3, 0.333, 1, 4, 0.25]]}, {"name": "PassesReceived", "headers": ["PLAYER_ID", "PLAYER_NAME_LAST_FIRST", "TEAM_NAME", "TEAM_ID", "TEAM_ABBREVIATION", "PASS_TYPE", "G", "PASS_FROM", "PASS_TEAMMATE_PLAYER_ID", "FREQUENCY", "PASS", "AST", "FGM", "FGA", "FG_PCT", "FG2M", "FG2A", "FG2_PCT", "FG3M", "FG3A", "FG3_PCT"], "rowSet": [[1628392, "Hartenstein, Isaiah", "New York Knicks", 1610612752, "NYK", "received", 75, "McBride, Miles", 1630540, 0.098, 155, 9, 10, 15, 0.667, 10, 15, 0.667, 0, 0, 0.0], [1628392, "Hartenstein, Isaiah", "New York Knicks", 1610612752, "NYK", "received", 75, "Flynn, Malachi", 1630201, 0.003, 4, 0, 0, 0, 0.0, 0, 0, 0.0, 0, 0, 0.0], [1628392, "Hartenstein, Isaiah", "New York Knicks", 1610612752, "NYK", "received", 75, "Quickley, Immanuel", 1630193, 0.07, 111, 10, 10, 24, 0.417, 9, 22, 0.409, 1, 2, 0.5], [1628392, "Hartenstein, Isaiah", "New York Knicks", 1610612752, "NYK", "received", 75, "Achiuwa, Precious", 1630173, 0.023, 37, 1, 1, 4, 0.25, 1, 4, 0.25, 0, 0, 0.0], [1628392, "Hartenstein, Isaiah", "New York Knicks", 1610612752, "NYK", "received", 75, "Grimes, Quentin", 1629656, 0.023, 37, 1, 1, 4, 0.25, 1, 4, 0.25, 0, 0, 0.0], [1628392, "Hartenstein, Isaiah", "New York Knicks", 1610612752, "NYK", "received", 75, "Barrett, RJ", 1629628, 0.025, 40, 7, 8, 14, 0.571, 8, 13, 0.615, 0, 1, 0.0], [1628392, "Hartenstein, Isaiah", "New York Knicks", 1610612752, "NYK", "received", 75, "Milton, Shake", 1629003, 0.001, 2, 0, 0, 1, 0.0, 0, 1, 0.0, 0, 0, 0.0], [1628392, "Hartenstein, Isaiah", "New York Knicks", 1610612752, "NYK", "received", 75, "DiVincenzo, Donte", 1628978, 0.172, 272, 27, 29, 55, 0.527, 29, 55, 0.527, 0, 0, 0.0], [1628392, "Hartenstein, Isaiah", "New York Knicks", 1610612752, "NYK", "received", 75, "Brunson, Jalen", 1628973, 0.268, 424, 59, 61, 96, 0.635, 61, 96, 0.635, 0, 0, 0.0], [1628392, "Hartenstein, Isaiah", "New York Knicks", 1610612752, "NYK", "received", 75, "Hart, Josh", 1628404, 0.188, 298, 29, 32, 55, 0.582, 32, 55, 0.582, 0, 0, 0.0], [1628392, "Hartenstein, Isaiah", "New York Knicks", 1610612752, "NYK", "received", 75, "Anunoby, OG", 1628384, 0.03, 47, 7, 8, 14, 0.571, 8, 14, 0.571, 0, 0, 0.0], [1628392, "Hartenstein, Isaiah", "New York Knicks", 1610612752, "NYK", "received", 75, "Randle, Julius", 203944, 0.07, 110, 2, 2, 12, 0.167, 2, 12, 0.167, 0, 0, 0.0], [1628392, "Hartenstein, Isaiah", "New York Knicks", 1610612752, "NYK", "received", 75, "Fournier, Evan", 203095, 0.001, 2, 0, 0, 0, 0.0, 0, 0, 0.0, 0, 0, 0.0], [1628392, "Hartenstein, Isaiah", "New York Knicks", 1610612752, "NYK", "received", 75, "Bogdanovic, Bojan", 202711, 0.013, 21, 1, 3, 3, 1.0, 3, 3, 1.0, 0, 0, 0.0], [1628392, "Hartenstein, Isaiah", "New York Knicks", 1610612752, "NYK", "received", 75, "Burks, Alec", 202692, 0.014, 22, 1, 1, 1, 1.0, 1, 1, 1.0, 0, 0, 0.0]]}]}