{"resource": "playerdashptpass", "parameters": {"PerMode": "Totals", "LeagueID": "00", "Season": "2023-24", "SeasonType": "Regular Season", "PlayerID": 1630559, "TeamID": 0, "Outcome": null, "Location": null, "Month": 0, "SeasonSegment": null, "DateFrom": null, "DateTo": null, "OpponentTeamID": 0, "VsConference": null, "VsDivision": null, "LastNGames": 0, "ISTRound": null}, "resultSets": [{"name": "PassesMade", "headers": ["PLAYER_ID", "PLAYER_NAME_LAST_FIRST", "TEAM_NAME", "TEAM_ID", "TEAM_ABBREVIATION", "PASS_TYPE", "G", "PASS_TO", "PASS_TEAMMATE_PLAYER_ID", "FREQUENCY", "PASS", "AST", "FGM", "FGA", "FG_PCT", "FG2M", "FG2A", "FG2_PCT", "FG3M", "FG3A", "FG3_PCT"], "rowSet": [[1630559, "Reaves, Austin", "Los Angeles Lakers", 1610612747, "LAL", "made", 81, "Hodge, D'Moi", 1641793, 0.0, 1, 0, 0, 0, 0.0, 0, 0, 0.0, 0, 0, 0.0], [1630559, "Reaves, Austin", "Los Angeles Lakers", 1610612747, "LAL", "made", 81, "Lewis, Maxwell", 1641721, 0.0, 1, 0, 0, 0, 0.0, 0, 0, 0.0, 0, 0, 0.0], [1630559, "Reaves, Austin", "Los Angeles Lakers", 1610612747, "LAL", "made", 81, "Hood-Schifino, Jalen", 1641720, 0.004, 13, 0, 0, 3, 0.0, 0, 2, 0.0, 0, 1, 0.0], [1630559, "Reaves, Austin", "Los Angeles Lakers", 1610612747, "LAL", "made", 81, "Christie, Max", 1631108, 0.027, 98, 13, 13, 32, 0.406, 4, 14, 0.286, 9, 18, 0.5], [1630559, "Reaves, Austin", "Los Angeles Lakers", 1610612747, "LAL", "made", 81, "Mays, Skylar", 1630219, 0.001, 3, 0, 0, 2, 0.0, 0, 1, 0.0, 0, 1, 0.0], [1630559, "Reaves, Austin", "Los Angeles Lakers", 1610612747, "LAL", "made", 81, "Hayes, Jaxson", 1629637, 0.03, 108, 15, 15, 21, 0.714, 15, 21, 0.714, 0, 0, 0.0], [1630559, "Reaves, Austin", "Los Angeles Lakers", 1610612747, "LAL", "made", 81, "Reddish, Cam", 1629629, 0.028, 99, 13, 13, 47, 0.277, 3, 13, 0.231, 10, 34, 0.294], [1630559, "Reaves, Austin", "Los Angeles Lakers", 1610612747, "LAL", "made", 81, "Vincent, Gabe", 1629216, 0.006, 23, 0, 1, 5, 0.2, 0, 1, 0.0, 1, 4, 0.25], [1630559, "Reaves, Austin", "Los Angeles Lakers", 1610612747, "LAL", "made", 81, "Hachimura, Rui", 1629060, 0.091, 328, 74, 83, 175, 0.474, 52, 112, 0.464, 31, 63, 0.492], [1630559, "Reaves, Austin", "Los Angeles Lakers", 1610612747, "LAL", "made", 81, "Vanderbilt, Jarred", 1629020, 0.009, 31, 8, 8, 15, 0.533, 4, 8, 0.5, 4, 7, 0.571], [1630559, "Reaves, Austin", "Los Angeles Lakers", 1610612747, "LAL", "made", 81, "Prince, Taurean", 1627752, 0.065, 235, 43, 47, 111, 0.423, 20, 35, 0.571, 27, 76, 0.355], [1630559, "Reaves, Austin", "Los Angeles Lakers", 1610612747, "LAL", "made", 81, "Wood, Christian", 1626174, 0.04, 144, 21, 23, 57, 0.404, 14, 30, 0.467, 9, 27, 0.333], [1630559, "Reaves, Austin", "Los Angeles Lakers", 1610612747, "LAL", "made", 81, "Russell, D'Angelo", 1626156, 0.161, 578, 45, 71, 158, 0.449, 33, 72, 0.458, 38, 86, 0.442], [1630559, "Reaves, Austin", "Los Angeles Lakers", 1610612747, "LAL", "made", 81, "Dinwiddie, Spencer", 203915, 0.028, 99, 5, 9, 25, 0.36, 4, 10, 0.4, 5, 15, 0.333], [1630559, "Reaves, Austin", "Los Angeles Lakers", 1610612747, "LAL", "made", 81, "Davis, Anthony", 203076, 0.251, 901, 94, 121, 292, 0.414, 116, 264, 0.439, 5, 28, 0.179], [1630559, "Reaves, Austin", "Los Angeles Lakers", 1610612747, "LAL", "made", 81, "James, LeBron", 2544, 0.26, 933, 103, 159, 322, 0.494, 135, 234, 0.577, 24, 88, 0.273]]}, {"name": "PassesReceived", "headers": ["PLAYER_ID", "PLAYER_NAME_LAST_FIRST", "TEAM_NAME", "TEAM_ID", "TEAM_ABBREVIATION", "PASS_TYPE", "G", "PASS_FROM", "PASS_TEAMMATE_PLAYER_ID", "FREQUENCY", "PASS", "AST", "FGM", "FGA", "FG_PCT", "FG2M", "FG2A", "FG2_PCT", "FG3M", "FG3A", "FG3_PCT"], "rowSet": [[1630559, "Reaves, Austin", "Los Angeles Lakers", 1610612747, "LAL", "received", 81, "Hood-Schifino, Jalen", 1641720, 0.004, 14, 1, 1, 4, 0.25, 1, 1, 1.0, 0, 3, 0.0], [1630559, "Reaves, Austin", "Los Angeles Lakers", 1610612747, "LAL", "received", 81, "Christie, Max", 1631108, 0.038, 141, 3, 14, 29, 0.483, 10, 21, 0.476, 4, 8, 0.5], [1630559, "Reaves, Austin", "Los Angeles Lakers", 1610612747, "LAL", "received", 81, "Castleton, Colin", 1630658, 0.0, 1, 0, 0, 0, 0.0, 0, 0, 0.0, 0, 0, 0.0], [1630559, "Reaves, Austin", "Los Angeles Lakers", 1610612747, "LAL", "received", 81, "Mays, Skylar", 1630219, 0.001, 4, 0, 0, 0, 0.0, 0, 0, 0.0, 0, 0, 0.0], [1630559, "Reaves, Austin", "Los Angeles Lakers", 1610612747, "LAL", "received", 81, "Hayes, Jaxson", 1629637, 0.05, 184, 7, 20, 52, 0.385, 15, 32, 0.469, 5, 20, 0.25], [1630559, "Reaves, Austin", "Los Angeles Lakers", 1610612747, "LAL", "received", 81, "Reddish, Cam", 1629629, 0.023, 84, 2, 7, 16, 0.438, 4, 9, 0.444, 3, 7, 0.429], [1630559, "Reaves, Austin", "Los Angeles Lakers", 1610612747, "LAL", "received", 81, "Vincent, Gabe", 1629216, 0.005, 19, 1, 1, 4, 0.25, 1, 4, 0.25, 0, 0, 0.0], [1630559, "Reaves, Austin", "Los Angeles Lakers", 1610612747, "LAL", "received", 81, "Hachimura, Rui", 1629060, 0.098, 362, 21, 43, 86, 0.5, 23, 42, 0.548, 20, 44, 0.455], [1630559, "Reaves, Austin", "Los Angeles Lakers", 1610612747, "LAL", "received", 81, "Vanderbilt, Jarred", 1629020, 0.021, 76, 3, 7, 17, 0.412, 4, 7, 0.571, 3, 10, 0.3], [1630559, "Reaves, Austin", "Los Angeles Lakers", 1610612747, "LAL", "received", 81, "Prince, Taurean", 1627752, 0.057, 210, 12, 28, 58, 0.483, 17, 33, 0.515, 11, 25, 0.44], [1630559, "Reaves, Austin", "Los Angeles Lakers", 1610612747, "LAL", "received", 81, "Wood, Christian", 1626174, 0.06, 220, 3, 17, 45, 0.378, 10, 30, 0.333, 7, 15, 0.467], [1630559, "Reaves, Austin", "Los Angeles Lakers", 1610612747, "LAL", "received", 81, "Russell, D'Angelo", 1626156, 0.137, 506, 55, 77, 152, 0.507, 41, 71, 0.577, 36, 81, 0.444], [1630559, "Reaves, Austin", "Los Angeles Lakers", 1610612747, "LAL", "received", 81, "Dinwiddie, Spencer", 203915, 0.025, 91, 6, 11, 28, 0.393, 7, 11, 0.636, 4, 17, 0.235], [1630559, "Reaves, Austin", "Los Angeles Lakers", 1610612747, "LAL", "received", 81, "Davis, Anthony", 203076, 0.246, 907, 38, 79, 190, 0.416, 57, 118, 0.483, 22, 72, 0.306], [1630559, "Reaves, Austin", "Los Angeles Lakers", 1610612747, "LAL", "received", 81, "James, LeBron", 2544, 0.236, 869, 73, 103, 222, 0.464, 76, 131, 0.58, 27, 91, 0.297]]}]}