{"resource": "playerdashptpass", "parameters": {"PerMode": "Totals", "LeagueID": "00", "Season": "2016-17", "SeasonType": "Regular Season", "PlayerID": 101138, "TeamID": 0, "Outcome": null, "Location": null, "Month": 0, "SeasonSegment": null, "DateFrom": null, "DateTo": null, "OpponentTeamID": 0, "VsConference": null, "VsDivision": null, "LastNGames": 0, "ISTRound": null}, "resultSets": [{"name": "PassesMade", "headers": ["PLAYER_ID", "PLAYER_NAME_LAST_FIRST", "TEAM_NAME", "TEAM_ID", "TEAM_ABBREVIATION", "PASS_TYPE", "G", "PASS_TO", "PASS_TEAMMATE_PLAYER_ID", "FREQUENCY", "PASS", "AST", "FGM", "FGA", "FG_PCT", "FG2M", "FG2A", "FG2_PCT", "FG3M", "FG3A", "FG3_PCT"], "rowSet": [[101138, "Bass, Brandon", "LA Clippers", 1610612746, "LAC", "made", 51, "Stone, Diamond", 1627754, 0.002, 1, 1, 1, 1, 1.0, 1, 1, 1.0, 0, 0, 0.0], [101138, "Bass, Brandon", "LA Clippers", 1610612746, "LAC", "made", 51, "Johnson, Brice", 1627744, 0.002, 1, 0, 0, 0, 0.0, 0, 0, 0.0, 0, 0, 0.0], [101138, "Bass, Brandon", "LA Clippers", 1610612746, "LAC", "made", 51, "Rivers, Austin", 203085, 0.238, 151, 4, 10, 28, 0.357, 4, 19, 0.211, 6, 9, 0.667], [101138, "Bass, Brandon", "LA Clippers", 1610612746, "LAC", "made", 51, "Johnson, Wesley", 202325, 0.054, 34, 2, 2, 10, 0.2, 1, 4, 0.25, 1, 6, 0.167], [101138, "Bass, Brandon", "LA Clippers", 1610612746, "LAC", "made", 51, "Griffin, Blake", 201933, 0.002, 1, 0, 0, 0, 0.0, 0, 0, 0.0, 0, 0, 0.0], [101138, "Bass, Brandon", "LA Clippers", 1610612746, "LAC", "made", 51, "Mbah a Moute, Luc", 201601, 0.003, 2, 0, 0, 1, 0.0, 0, 1, 0.0, 0, 0, 0.0], [101138, "Bass, Brandon", "LA Clippers", 1610612746, "LAC", "made", 51, "Jordan, DeAndre", 201599, 0.011, 7, 3, 3, 3, 1.0, 3, 3, 1.0, 0, 0, 0.0], [101138, "Bass, Brandon", "LA Clippers", 1610612746, "LAC", "made", 51, "Speights, Marreese", 201578, 0.058, 37, 6, 6, 14, 0.429, 3, 7, 0.429, 3, 7, 0.429], [101138, "Bass, Brandon", "LA Clippers", 1610612746, "LAC", "made", 51, "Redick, JJ", 200755, 0.025, 16, 0, 1, 6, 0.167, 0, 2, 0.0, 1, 4, 0.25], [101138, "Bass, Brandon", "LA Clippers", 1610612746, "LAC", "made", 51, "Anderson, Alan", 101187, 0.041, 26, 3, 4, 10, 0.4, 0, 3, 0.0, 4, 7, 0.571], [101138, "Bass, Brandon", "LA Clippers", 1610612746, "LAC", "made", 51, "Felton, Raymond", 101109, 0.258, 164, 1, 5, 22, 0.227, 5, 17, 0.294, 0, 5, 0.0], [101138, "Bass, Brandon", "LA Clippers", 1610612746, "LAC", "made", 51, "Paul, Chris", 101108, 0.054, 34, 0, 2, 2, 1.0, 2, 2, 1.0, 0, 0, 0.0], [101138, "Bass, Brandon", "LA Clippers", 1610612746, "LAC", "made", 51, "Crawford, Jamal", 2037, 0.25, 159, 4, 10, 34, 0.294, 5, 20, 0.25, 5, 14, 0.357], [101138, "Bass, Brandon", "LA Clippers", 1610612746, "LAC", "made", 51, "Pierce, Paul", 1718, 0.003, 2, 0, 0, 0, 0.0, 0, 0, 0.0, 0, 0, 0.0]]}, {"name": "PassesReceived", "headers": ["PLAYER_ID", "PLAYER_NAME_LAST_FIRST", "TEAM_NAME", "TEAM_ID", "TEAM_ABBREVIATION", "PASS_TYPE", "G", "PASS_FROM", "PASS_TEAMMATE_PLAYER_ID", "FREQUENCY", "PASS", "AST", "FGM", "FGA", "FG_PCT", "FG2M", "FG2A", "FG2_PCT", "FG3M", "FG3A", "FG3_PCT"], "rowSet": [[101138, "Bass, Brandon", "LA Clippers", 1610612746, "LAC", "received", 51, "Stone, Diamond", 1627754, 0.002, 1, 0, 0, 0, 0.0, 0, 0, 0.0, 0, 0, 0.0], [101138, "Bass, Brandon", "LA Clippers", 1610612746, "LAC", "received", 51, "Johnson, Brice", 1627744, 0.002, 1, 0, 0, 0, 0.0, 0, 0, 0.0, 0, 0, 0.0], [101138, "Bass, Brandon", "LA Clippers", 1610612746, "LAC", "received", 51, "Rivers, Austin", 203085, 0.201, 114, 12, 16, 33, 0.485, 16, 33, 0.485, 0, 0, 0.0], [101138, "Bass, Brandon", "LA Clippers", 1610612746, "LAC", "received", 51, "Johnson, Wesley", 202325, 0.049, 28, 3, 6, 10, 0.6, 6, 10, 0.6, 0, 0, 0.0], [101138, "Bass, Brandon", "LA Clippers", 1610612746, "LAC", "received", 51, "Mbah a Moute, Luc", 201601, 0.011, 6, 0, 0, 2, 0.0, 0, 2, 0.0, 0, 0, 0.0], [101138, "Bass, Brandon", "LA Clippers", 1610612746, "LAC", "received", 51, "Jordan, DeAndre", 201599, 0.012, 7, 0, 1, 1, 1.0, 1, 1, 1.0, 0, 0, 0.0], [101138, "Bass, Brandon", "LA Clippers", 1610612746, "LAC", "received", 51, "Speights, Marreese", 201578, 0.058, 33, 7, 7, 10, 0.7, 6, 9, 0.667, 1, 1, 1.0], [101138, "Bass, Brandon", "LA Clippers", 1610612746, "LAC", "received", 51, "Redick, JJ", 200755, 0.035, 20, 2, 2, 3, 0.667, 2, 3, 0.667, 0, 0, 0.0], [101138, "Bass, Brandon", "LA Clippers", 1610612746, "LAC", "received", 51, "Anderson, Alan", 101187, 0.037, 21, 3, 7, 12, 0.583, 7, 12, 0.583, 0, 0, 0.0], [101138, "Bass, Brandon", "LA Clippers", 1610612746, "LAC", "received", 51, "Felton, Raymond", 101109, 0.265, 150, 11, 19, 44, 0.432, 19, 42, 0.452, 0, 2, 0.0], [101138, "Bass, Brandon", "LA Clippers", 1610612746, "LAC", "received", 51, "Paul, Chris", 101108, 0.058, 33, 9, 10, 19, 0.526, 10, 19, 0.526, 0, 0, 0.0], [101138, "Bass, Brandon", "LA Clippers", 1610612746, "LAC", "received", 51, "Crawford, Jamal", 2037, 0.268, 152, 25, 27, 56, 0.482, 27, 56, 0.482, 0, 0, 0.0], [101138, "Bass, Brandon", "LA Clippers", 1610612746, "LAC", "received", 51, "Pierce, Paul", 1718, 0.002, 1, 1, 1, 1, 1.0, 1, 1, 1.0, 0, 0, 0.0]]}]}