{"resource": "playerdashptpass", "parameters": {"PerMode": "Totals", "LeagueID": "00", "Season": "2018-19", "SeasonType": "Regular Season", "PlayerID": 1627827, "TeamID": 0, "Outcome": null, "Location": null, "Month": 0, "SeasonSegment": null, "DateFrom": null, "DateTo": null, "OpponentTeamID": 0, "VsConference": null, "VsDivision": null, "LastNGames": 0, "ISTRound": null}, "resultSets": [{"name": "PassesMade", "headers": ["PLAYER_ID", "PLAYER_NAME_LAST_FIRST", "TEAM_NAME", "TEAM_ID", "TEAM_ABBREVIATION", "PASS_TYPE", "G", "PASS_TO", "PASS_TEAMMATE_PLAYER_ID", "FREQUENCY", "PASS", "AST", "FGM", "FGA", "FG_PCT", "FG2M", "FG2A", "FG2_PCT", "FG3M", "FG3A", "FG3_PCT"], "rowSet": [[1627827, "Finney-Smith, Dorian", "Dallas Mavericks", 1610612742, "DAL", "made", 81, "Broekhoff, Ryan", 1629151, 0.011, 20, 1, 1, 6, 0.167, 1, 2, 0.5, 0, 4, 0.0], [1627827, "Finney-Smith, Dorian", "Dallas Mavericks", 1610612742, "DAL", "made", 81, "Macon, Daryl", 1629133, 0.004, 8, 1, 1, 2, 0.5, 0, 1, 0.0, 1, 1, 1.0], [1627827, "Finney-Smith, Dorian", "Dallas Mavericks", 1610612742, "DAL", "made", 81, "Don\u010di\u0107, Luka", 1629029, 0.187, 333, 12, 35, 81, 0.432, 23, 44, 0.523, 12, 37, 0.324], [1627827, "Finney-Smith, Dorian", "Dallas Mavericks", 1610612742, "DAL", "made", 81, "Brunson, Jalen", 1628973, 0.156, 277, 10, 24, 45, 0.533, 19, 27, 0.704, 5, 18, 0.278], [1627827, "Finney-Smith, Dorian", "Dallas Mavericks", 1610612742, "DAL", "made", 81, "Kleber, Maxi", 1628467, 0.057, 102, 15, 16, 36, 0.444, 8, 13, 0.615, 8, 23, 0.348], [1627827, "Finney-Smith, Dorian", "Dallas Mavericks", 1610612742, "DAL", "made", 81, "Jackson, Justin", 1628382, 0.011, 20, 7, 7, 13, 0.538, 5, 8, 0.625, 2, 5, 0.4], [1627827, "Finney-Smith, Dorian", "Dallas Mavericks", 1610612742, "DAL", "made", 81, "Smith Jr., Dennis", 1628372, 0.071, 127, 3, 8, 20, 0.4, 7, 14, 0.5, 1, 6, 0.167], [1627827, "Finney-Smith, Dorian", "Dallas Mavericks", 1610612742, "DAL", "made", 81, "Mejri, Salah", 1626257, 0.021, 38, 4, 4, 8, 0.5, 3, 5, 0.6, 1, 3, 0.333], [1627827, "Finney-Smith, Dorian", "Dallas Mavericks", 1610612742, "DAL", "made", 81, "Powell, Dwight", 203939, 0.07, 124, 8, 11, 32, 0.344, 9, 22, 0.409, 2, 10, 0.2], [1627827, "Finney-Smith, Dorian", "Dallas Mavericks", 1610612742, "DAL", "made", 81, "Burke, Trey", 203504, 0.037, 66, 2, 4, 17, 0.235, 0, 8, 0.0, 4, 9, 0.444], [1627827, "Finney-Smith, Dorian", "Dallas Mavericks", 1610612742, "DAL", "made", 81, "Hardaway Jr., Tim", 203501, 0.038, 68, 7, 11, 30, 0.367, 10, 20, 0.5, 1, 10, 0.1], [1627827, "Finney-Smith, Dorian", "Dallas Mavericks", 1610612742, "DAL", "made", 81, "Barnes, Harrison", 203084, 0.042, 74, 7, 12, 48, 0.25, 6, 24, 0.25, 6, 24, 0.25], [1627827, "Finney-Smith, Dorian", "Dallas Mavericks", 1610612742, "DAL", "made", 81, "Matthews, Wesley", 202083, 0.031, 55, 6, 9, 21, 0.429, 6, 11, 0.545, 3, 10, 0.3], [1627827, "Finney-Smith, Dorian", "Dallas Mavericks", 1610612742, "DAL", "made", 81, "Jordan, DeAndre", 201599, 0.035, 63, 1, 1, 5, 0.2, 1, 5, 0.2, 0, 0, 0.0], [1627827, "Finney-Smith, Dorian", "Dallas Mavericks", 1610612742, "DAL", "made", 81, "Lee, Courtney", 201584, 0.002, 4, 2, 2, 3, 0.667, 0, 0, 0.0, 2, 3, 0.667], [1627827, "Finney-Smith, Dorian", "Dallas Mavericks", 1610612742, "DAL", "made", 81, "Barea, J.J.", 200826, 0.15, 267, 1, 12, 47, 0.255, 10, 31, 0.323, 2, 16, 0.125], [1627827, "Finney-Smith, Dorian", "Dallas Mavericks", 1610612742, "DAL", "made", 81, "Harris, Devin", 2734, 0.061, 108, 4, 5, 24, 0.208, 1, 11, 0.091, 4, 13, 0.308], [1627827, "Finney-Smith, Dorian", "Dallas Mavericks", 1610612742, "DAL", "made", 81, "Nowitzki, Dirk", 1717, 0.015, 27, 4, 7, 15, 0.467, 4, 8, 0.5, 3, 7, 0.429]]}, {"name": "PassesReceived", "headers": ["PLAYER_ID", "PLAYER_NAME_LAST_FIRST", "TEAM_NAME", "TEAM_ID", "TEAM_ABBREVIATION", "PASS_TYPE", "G", "PASS_FROM", "PASS_TEAMMATE_PLAYER_ID", "FREQUENCY", "PASS", "AST", "FGM", "FGA", "FG_PCT", "FG2M", "FG2A", "FG2_PCT", "FG3M", "FG3A", "FG3_PCT"], "rowSet": [[1627827, "Finney-Smith, Dorian", "Dallas Mavericks", 1610612742, "DAL", "received", 81, "Broekhoff, Ryan", 1629151, 0.009, 15, 1, 1, 4, 0.25, 1, 4, 0.25, 0, 0, 0.0], [1627827, "Finney-Smith, Dorian", "Dallas Mavericks", 1610612742, "DAL", "received", 81, "Macon, Daryl", 1629133, 0.004, 6, 0, 0, 1, 0.0, 0, 0, 0.0, 0, 1, 0.0], [1627827, "Finney-Smith, Dorian", "Dallas Mavericks", 1610612742, "DAL", "received", 81, "Don\u010di\u0107, Luka", 1629029, 0.201, 323, 33, 36, 96, 0.375, 19, 38, 0.5, 17, 58, 0.293], [1627827, "Finney-Smith, Dorian", "Dallas Mavericks", 1610612742, "DAL", "received", 81, "Brunson, Jalen", 1628973, 0.182, 292, 26, 32, 86, 0.372, 22, 41, 0.537, 10, 45, 0.222], [1627827, "Finney-Smith, Dorian", "Dallas Mavericks", 1610612742, "DAL", "received", 81, "Antetokounmpo, Kostas", 1628961, 0.001, 1, 0, 0, 0, 0.0, 0, 0, 0.0, 0, 0, 0.0], [1627827, "Finney-Smith, Dorian", "Dallas Mavericks", 1610612742, "DAL", "received", 81, "Kleber, Maxi", 1628467, 0.048, 77, 7, 8, 16, 0.5, 3, 6, 0.5, 5, 10, 0.5], [1627827, "Finney-Smith, Dorian", "Dallas Mavericks", 1610612742, "DAL", "received", 81, "Jackson, Justin", 1628382, 0.015, 24, 2, 2, 9, 0.222, 1, 5, 0.2, 1, 4, 0.25], [1627827, "Finney-Smith, Dorian", "Dallas Mavericks", 1610612742, "DAL", "received", 81, "Smith Jr., Dennis", 1628372, 0.085, 137, 16, 18, 34, 0.529, 12, 16, 0.75, 6, 18, 0.333], [1627827, "Finney-Smith, Dorian", "Dallas Mavericks", 1610612742, "DAL", "received", 81, "Mejri, Salah", 1626257, 0.025, 40, 1, 1, 12, 0.083, 1, 5, 0.2, 0, 7, 0.0], [1627827, "Finney-Smith, Dorian", "Dallas Mavericks", 1610612742, "DAL", "received", 81, "Powell, Dwight", 203939, 0.063, 101, 16, 16, 29, 0.552, 11, 16, 0.688, 5, 13, 0.385], [1627827, "Finney-Smith, Dorian", "Dallas Mavericks", 1610612742, "DAL", "received", 81, "Burke, Trey", 203504, 0.037, 59, 6, 7, 22, 0.318, 3, 10, 0.3, 4, 12, 0.333], [1627827, "Finney-Smith, Dorian", "Dallas Mavericks", 1610612742, "DAL", "received", 81, "Hardaway Jr., Tim", 203501, 0.036, 57, 5, 5, 16, 0.313, 1, 6, 0.167, 4, 10, 0.4], [1627827, "Finney-Smith, Dorian", "Dallas Mavericks", 1610612742, "DAL", "received", 81, "Barnes, Harrison", 203084, 0.036, 57, 6, 7, 19, 0.368, 5, 10, 0.5, 2, 9, 0.222], [1627827, "Finney-Smith, Dorian", "Dallas Mavericks", 1610612742, "DAL", "received", 81, "Matthews, Wesley", 202083, 0.016, 26, 9, 9, 12, 0.75, 4, 6, 0.667, 5, 6, 0.833], [1627827, "Finney-Smith, Dorian", "Dallas Mavericks", 1610612742, "DAL", "received", 81, "Jordan, DeAndre", 201599, 0.042, 68, 3, 5, 19, 0.263, 3, 9, 0.333, 2, 10, 0.2], [1627827, "Finney-Smith, Dorian", "Dallas Mavericks", 1610612742, "DAL", "received", 81, "Lee, Courtney", 201584, 0.009, 15, 2, 2, 8, 0.25, 1, 5, 0.2, 1, 3, 0.333], [1627827, "Finney-Smith, Dorian", "Dallas Mavericks", 1610612742, "DAL", "received", 81, "Barea, J.J.", 200826, 0.125, 201, 21, 24, 48, 0.5, 15, 25, 0.6, 9, 23, 0.391], [1627827, "Finney-Smith, Dorian", "Dallas Mavericks", 1610612742, "DAL", "received", 81, "Harris, Devin", 2734, 0.049, 79, 9, 12, 30, 0.4, 5, 17, 0.294, 7, 13, 0.538], [1627827, "Finney-Smith, Dorian", "Dallas Mavericks", 1610612742, "DAL", "received", 81, "Nowitzki, Dirk", 1717, 0.016, 25, 1, 1, 5, 0.2, 1, 3, 0.333, 0, 2, 0.0]]}]}