{"resource": "playerdashptpass", "parameters": {"PerMode": "Totals", "LeagueID": "00", "Season": "2014-15", "SeasonType": "Regular Season", "PlayerID": 202696, "TeamID": 0, "Outcome": null, "Location": null, "Month": 0, "SeasonSegment": null, "DateFrom": null, "DateTo": null, "OpponentTeamID": 0, "VsConference": null, "VsDivision": null, "LastNGames": 0, "ISTRound": null}, "resultSets": [{"name": "PassesMade", "headers": ["PLAYER_ID", "PLAYER_NAME_LAST_FIRST", "TEAM_NAME", "TEAM_ID", "TEAM_ABBREVIATION", "PASS_TYPE", "G", "PASS_TO", "PASS_TEAMMATE_PLAYER_ID", "FREQUENCY", "PASS", "AST", "FGM", "FGA", "FG_PCT", "FG2M", "FG2A", "FG2_PCT", "FG3M", "FG3A", "FG3_PCT"], "rowSet": [[202696, "Vu\u010devi\u0107, Nikola", "Orlando Magic", 1610612753, "ORL", "made", 74, "Gordon, Aaron", 203932, 0.02, 47, 5, 7, 21, 0.333, 5, 16, 0.313, 2, 5, 0.4], [202696, "Vu\u010devi\u0107, Nikola", "Orlando Magic", 1610612753, "ORL", "made", 74, "Marble, Devyn", 203906, 0.003, 8, 2, 2, 5, 0.4, 0, 1, 0.0, 2, 4, 0.5], [202696, "Vu\u010devi\u0107, Nikola", "Orlando Magic", 1610612753, "ORL", "made", 74, "Payton, Elfrid", 203901, 0.347, 821, 12, 52, 138, 0.377, 50, 129, 0.388, 2, 9, 0.222], [202696, "Vu\u010devi\u0107, Nikola", "Orlando Magic", 1610612753, "ORL", "made", 74, "Oladipo, Victor", 203506, 0.22, 520, 25, 46, 154, 0.299, 36, 111, 0.324, 10, 43, 0.233], [202696, "Vu\u010devi\u0107, Nikola", "Orlando Magic", 1610612753, "ORL", "made", 74, "Dedmon, Dewayne", 203473, 0.008, 20, 2, 2, 11, 0.182, 2, 11, 0.182, 0, 0, 0.0], [202696, "Vu\u010devi\u0107, Nikola", "Orlando Magic", 1610612753, "ORL", "made", 74, "O'Quinn, Kyle", 203124, 0.013, 30, 4, 5, 9, 0.556, 2, 5, 0.4, 3, 4, 0.75], [202696, "Vu\u010devi\u0107, Nikola", "Orlando Magic", 1610612753, "ORL", "made", 74, "Fournier, Evan", 203095, 0.08, 190, 23, 37, 83, 0.446, 23, 49, 0.469, 14, 34, 0.412], [202696, "Vu\u010devi\u0107, Nikola", "Orlando Magic", 1610612753, "ORL", "made", 74, "Nicholson, Andrew", 203094, 0.008, 19, 3, 6, 11, 0.545, 3, 6, 0.5, 3, 5, 0.6], [202696, "Vu\u010devi\u0107, Nikola", "Orlando Magic", 1610612753, "ORL", "made", 74, "Harkless, Maurice", 203090, 0.01, 23, 1, 1, 8, 0.125, 1, 3, 0.333, 0, 5, 0.0], [202696, "Vu\u010devi\u0107, Nikola", "Orlando Magic", 1610612753, "ORL", "made", 74, "Harris, Tobias", 202699, 0.132, 311, 44, 57, 138, 0.413, 47, 98, 0.48, 10, 40, 0.25], [202696, "Vu\u010devi\u0107, Nikola", "Orlando Magic", 1610612753, "ORL", "made", 74, "Frye, Channing", 101112, 0.049, 116, 20, 21, 50, 0.42, 2, 12, 0.167, 19, 38, 0.5], [202696, "Vu\u010devi\u0107, Nikola", "Orlando Magic", 1610612753, "ORL", "made", 74, "Gordon, Ben", 2732, 0.017, 41, 3, 3, 11, 0.273, 3, 6, 0.5, 0, 5, 0.0], [202696, "Vu\u010devi\u0107, Nikola", "Orlando Magic", 1610612753, "ORL", "made", 74, "Green, Willie", 2584, 0.048, 114, 4, 7, 22, 0.318, 6, 10, 0.6, 1, 12, 0.083], [202696, "Vu\u010devi\u0107, Nikola", "Orlando Magic", 1610612753, "ORL", "made", 74, "Ridnour, Luke", 2557, 0.044, 105, 1, 3, 11, 0.273, 2, 7, 0.286, 1, 4, 0.25]]}, {"name": "PassesReceived", "headers": ["PLAYER_ID", "PLAYER_NAME_LAST_FIRST", "TEAM_NAME", "TEAM_ID", "TEAM_ABBREVIATION", "PASS_TYPE", "G", "PASS_FROM", "PASS_TEAMMATE_PLAYER_ID", "FREQUENCY", "PASS", "AST", "FGM", "FGA", "FG_PCT", "FG2M", "FG2A", "FG2_PCT", "FG3M", "FG3A", "FG3_PCT"], "rowSet": [[202696, "Vu\u010devi\u0107, Nikola", "Orlando Magic", 1610612753, "ORL", "received", 74, "Gordon, Aaron", 203932, 0.021, 53, 6, 11, 17, 0.647, 11, 17, 0.647, 0, 0, 0.0], [202696, "Vu\u010devi\u0107, Nikola", "Orlando Magic", 1610612753, "ORL", "received", 74, "Marble, Devyn", 203906, 0.01, 25, 7, 9, 12, 0.75, 9, 12, 0.75, 0, 0, 0.0], [202696, "Vu\u010devi\u0107, Nikola", "Orlando Magic", 1610612753, "ORL", "received", 74, "Payton, Elfrid", 203901, 0.354, 905, 156, 200, 425, 0.471, 199, 424, 0.469, 1, 1, 1.0], [202696, "Vu\u010devi\u0107, Nikola", "Orlando Magic", 1610612753, "ORL", "received", 74, "Oladipo, Victor", 203506, 0.232, 593, 101, 127, 251, 0.506, 127, 250, 0.508, 0, 1, 0.0], [202696, "Vu\u010devi\u0107, Nikola", "Orlando Magic", 1610612753, "ORL", "received", 74, "Dedmon, Dewayne", 203473, 0.005, 14, 1, 1, 1, 1.0, 1, 1, 1.0, 0, 0, 0.0], [202696, "Vu\u010devi\u0107, Nikola", "Orlando Magic", 1610612753, "ORL", "received", 74, "O'Quinn, Kyle", 203124, 0.019, 49, 8, 10, 21, 0.476, 10, 21, 0.476, 0, 0, 0.0], [202696, "Vu\u010devi\u0107, Nikola", "Orlando Magic", 1610612753, "ORL", "received", 74, "Fournier, Evan", 203095, 0.088, 224, 34, 46, 92, 0.5, 46, 92, 0.5, 0, 0, 0.0], [202696, "Vu\u010devi\u0107, Nikola", "Orlando Magic", 1610612753, "ORL", "received", 74, "Nicholson, Andrew", 203094, 0.006, 16, 6, 6, 12, 0.5, 6, 12, 0.5, 0, 0, 0.0], [202696, "Vu\u010devi\u0107, Nikola", "Orlando Magic", 1610612753, "ORL", "received", 74, "Harkless, Maurice", 203090, 0.013, 34, 3, 5, 8, 0.625, 5, 8, 0.625, 0, 0, 0.0], [202696, "Vu\u010devi\u0107, Nikola", "Orlando Magic", 1610612753, "ORL", "received", 74, "Harris, Tobias", 202699, 0.111, 284, 37, 53, 112, 0.473, 53, 111, 0.477, 0, 1, 0.0], [202696, "Vu\u010devi\u0107, Nikola", "Orlando Magic", 1610612753, "ORL", "received", 74, "Frye, Channing", 101112, 0.041, 106, 15, 21, 52, 0.404, 20, 49, 0.408, 1, 3, 0.333], [202696, "Vu\u010devi\u0107, Nikola", "Orlando Magic", 1610612753, "ORL", "received", 74, "Gordon, Ben", 2732, 0.018, 47, 8, 11, 19, 0.579, 11, 19, 0.579, 0, 0, 0.0], [202696, "Vu\u010devi\u0107, Nikola", "Orlando Magic", 1610612753, "ORL", "received", 74, "Green, Willie", 2584, 0.036, 91, 10, 17, 31, 0.548, 17, 31, 0.548, 0, 0, 0.0], [202696, "Vu\u010devi\u0107, Nikola", "Orlando Magic", 1610612753, "ORL", "received", 74, "Ridnour, Luke", 2557, 0.046, 118, 17, 24, 56, 0.429, 24, 56, 0.429, 0, 0, 0.0]]}]}