{"resource": "playerdashptpass", "parameters": {"PerMode": "Totals", "LeagueID": "00", "Season": "2014-15", "SeasonType": "Regular Season", "PlayerID": 201977, "TeamID": 0, "Outcome": null, "Location": null, "Month": 0, "SeasonSegment": null, "DateFrom": null, "DateTo": null, "OpponentTeamID": 0, "VsConference": null, "VsDivision": null, "LastNGames": 0, "ISTRound": null}, "resultSets": [{"name": "PassesMade", "headers": ["PLAYER_ID", "PLAYER_NAME_LAST_FIRST", "TEAM_NAME", "TEAM_ID", "TEAM_ABBREVIATION", "PASS_TYPE", "G", "PASS_TO", "PASS_TEAMMATE_PLAYER_ID", "FREQUENCY", "PASS", "AST", "FGM", "FGA", "FG_PCT", "FG2M", "FG2A", "FG2_PCT", "FG3M", "FG3A", "FG3_PCT"], "rowSet": [[201977, "Thornton, Marcus", "Boston Celtics", 1610612738, "BOS", "made", 48, "Powell, Dwight", 203939, 0.002, 1, 0, 0, 1, 0.0, 0, 1, 0.0, 0, 0, 0.0], [201977, "Thornton, Marcus", "Boston Celtics", 1610612738, "BOS", "made", 48, "Smart, Marcus", 203935, 0.125, 74, 4, 4, 17, 0.235, 0, 1, 0.0, 4, 16, 0.25], [201977, "Thornton, Marcus", "Boston Celtics", 1610612738, "BOS", "made", 48, "Young, James", 203923, 0.008, 5, 0, 0, 3, 0.0, 0, 0, 0.0, 0, 3, 0.0], [201977, "Thornton, Marcus", "Boston Celtics", 1610612738, "BOS", "made", 48, "Pressey, Phil", 203515, 0.059, 35, 0, 0, 6, 0.0, 0, 3, 0.0, 0, 3, 0.0], [201977, "Thornton, Marcus", "Boston Celtics", 1610612738, "BOS", "made", 48, "Olynyk, Kelly", 203482, 0.076, 45, 6, 7, 16, 0.438, 5, 11, 0.455, 2, 5, 0.4], [201977, "Thornton, Marcus", "Boston Celtics", 1610612738, "BOS", "made", 48, "Crowder, Jae", 203109, 0.04, 24, 1, 2, 3, 0.667, 2, 3, 0.667, 0, 0, 0.0], [201977, "Thornton, Marcus", "Boston Celtics", 1610612738, "BOS", "made", 48, "Sullinger, Jared", 203096, 0.113, 67, 3, 8, 20, 0.4, 8, 19, 0.421, 0, 1, 0.0], [201977, "Thornton, Marcus", "Boston Celtics", 1610612738, "BOS", "made", 48, "Zeller, Tyler", 203092, 0.062, 37, 7, 11, 20, 0.55, 11, 20, 0.55, 0, 0, 0.0], [201977, "Thornton, Marcus", "Boston Celtics", 1610612738, "BOS", "made", 48, "Bradley, Avery", 202340, 0.025, 15, 1, 1, 7, 0.143, 1, 4, 0.25, 0, 3, 0.0], [201977, "Thornton, Marcus", "Boston Celtics", 1610612738, "BOS", "made", 48, "Turner, Evan", 202323, 0.128, 76, 1, 5, 12, 0.417, 5, 9, 0.556, 0, 3, 0.0], [201977, "Thornton, Marcus", "Boston Celtics", 1610612738, "BOS", "made", 48, "Green, Jeff", 201145, 0.02, 12, 0, 1, 7, 0.143, 1, 4, 0.25, 0, 3, 0.0], [201977, "Thornton, Marcus", "Boston Celtics", 1610612738, "BOS", "made", 48, "Rondo, Rajon", 200765, 0.052, 31, 0, 0, 2, 0.0, 0, 1, 0.0, 0, 1, 0.0], [201977, "Thornton, Marcus", "Boston Celtics", 1610612738, "BOS", "made", 48, "Bass, Brandon", 101138, 0.118, 70, 9, 12, 30, 0.4, 12, 30, 0.4, 0, 0, 0.0], [201977, "Thornton, Marcus", "Boston Celtics", 1610612738, "BOS", "made", 48, "Prince, Tayshaun", 2419, 0.019, 11, 1, 2, 2, 1.0, 2, 2, 1.0, 0, 0, 0.0], [201977, "Thornton, Marcus", "Boston Celtics", 1610612738, "BOS", "made", 48, "Wallace, Gerald", 2222, 0.015, 9, 0, 0, 0, 0.0, 0, 0, 0.0, 0, 0, 0.0], [201977, "Thornton, Marcus", "Phoenix Suns", 1610612756, "PHX", "made", 48, "Warren, T.J.", 203933, 0.012, 7, 1, 1, 1, 1.0, 1, 1, 1.0, 0, 0, 0.0], [201977, "Thornton, Marcus", "Phoenix Suns", 1610612756, "PHX", "made", 48, "Curry, Seth", 203552, 0.002, 1, 0, 0, 1, 0.0, 0, 0, 0.0, 0, 1, 0.0], [201977, "Thornton, Marcus", "Phoenix Suns", 1610612756, "PHX", "made", 48, "Bullock Jr., Reggie", 203493, 0.005, 3, 0, 0, 1, 0.0, 0, 0, 0.0, 0, 1, 0.0], [201977, "Thornton, Marcus", "Phoenix Suns", 1610612756, "PHX", "made", 48, "Goodwin, Archie", 203462, 0.015, 9, 0, 0, 0, 0.0, 0, 0, 0.0, 0, 0, 0.0], [201977, "Thornton, Marcus", "Phoenix Suns", 1610612756, "PHX", "made", 48, "Len, Alex", 203458, 0.003, 2, 0, 0, 0, 0.0, 0, 0, 0.0, 0, 0, 0.0], [201977, "Thornton, Marcus", "Phoenix Suns", 1610612756, "PHX", "made", 48, "Morris Sr., Marcus", 202694, 0.01, 6, 0, 1, 2, 0.5, 1, 1, 1.0, 0, 1, 0.0], [201977, "Thornton, Marcus", "Phoenix Suns", 1610612756, "PHX", "made", 48, "Morris, Markieff", 202693, 0.015, 9, 1, 2, 4, 0.5, 2, 4, 0.5, 0, 0, 0.0], [201977, "Thornton, Marcus", "Phoenix Suns", 1610612756, "PHX", "made", 48, "Knight, Brandon", 202688, 0.012, 7, 0, 0, 2, 0.0, 0, 1, 0.0, 0, 1, 0.0], [201977, "Thornton, Marcus", "Phoenix Suns", 1610612756, "PHX", "made", 48, "Bledsoe, Eric", 202339, 0.039, 23, 0, 0, 2, 0.0, 0, 1, 0.0, 0, 1, 0.0], [201977, "Thornton, Marcus", "Phoenix Suns", 1610612756, "PHX", "made", 48, "Wright, Brandan", 201148, 0.012, 7, 0, 1, 2, 0.5, 1, 2, 0.5, 0, 0, 0.0], [201977, "Thornton, Marcus", "Phoenix Suns", 1610612756, "PHX", "made", 48, "Tucker, P.J.", 200782, 0.007, 4, 0, 0, 0, 0.0, 0, 0, 0.0, 0, 0, 0.0], [201977, "Thornton, Marcus", "Phoenix Suns", 1610612756, "PHX", "made", 48, "Barron, Earl", 2853, 0.005, 3, 0, 0, 2, 0.0, 0, 2, 0.0, 0, 0, 0.0]]}, {"name": "PassesReceived", "headers": ["PLAYER_ID", "PLAYER_NAME_LAST_FIRST", "TEAM_NAME", "TEAM_ID", "TEAM_ABBREVIATION", "PASS_TYPE", "G", "PASS_FROM", "PASS_TEAMMATE_PLAYER_ID", "FREQUENCY", "PASS", "AST", "FGM", "FGA", "FG_PCT", "FG2M", "FG2A", "FG2_PCT", "FG3M", "FG3A", "FG3_PCT"], "rowSet": [[201977, "Thornton, Marcus", "Boston Celtics", 1610612738, "BOS", "received", 48, "Smart, Marcus", 203935, 0.161, 132, 14, 18, 46, 0.391, 7, 26, 0.269, 11, 20, 0.55], [201977, "Thornton, Marcus", "Boston Celtics", 1610612738, "BOS", "received", 48, "Young, James", 203923, 0.011, 9, 4, 4, 5, 0.8, 1, 1, 1.0, 3, 4, 0.75], [201977, "Thornton, Marcus", "Boston Celtics", 1610612738, "BOS", "received", 48, "Pressey, Phil", 203515, 0.056, 46, 4, 7, 18, 0.389, 5, 14, 0.357, 2, 4, 0.5], [201977, "Thornton, Marcus", "Boston Celtics", 1610612738, "BOS", "received", 48, "Olynyk, Kelly", 203482, 0.077, 63, 8, 10, 26, 0.385, 5, 15, 0.333, 5, 11, 0.455], [201977, "Thornton, Marcus", "Boston Celtics", 1610612738, "BOS", "received", 48, "Crowder, Jae", 203109, 0.024, 20, 2, 2, 5, 0.4, 0, 3, 0.0, 2, 2, 1.0], [201977, "Thornton, Marcus", "Boston Celtics", 1610612738, "BOS", "received", 48, "Sullinger, Jared", 203096, 0.099, 81, 10, 14, 37, 0.378, 8, 23, 0.348, 6, 14, 0.429], [201977, "Thornton, Marcus", "Boston Celtics", 1610612738, "BOS", "received", 48, "Zeller, Tyler", 203092, 0.057, 47, 6, 9, 21, 0.429, 9, 16, 0.563, 0, 5, 0.0], [201977, "Thornton, Marcus", "Boston Celtics", 1610612738, "BOS", "received", 48, "Bradley, Avery", 202340, 0.024, 20, 2, 2, 9, 0.222, 0, 4, 0.0, 2, 5, 0.4], [201977, "Thornton, Marcus", "Boston Celtics", 1610612738, "BOS", "received", 48, "Turner, Evan", 202323, 0.152, 125, 13, 15, 45, 0.333, 6, 23, 0.261, 9, 22, 0.409], [201977, "Thornton, Marcus", "Boston Celtics", 1610612738, "BOS", "received", 48, "Green, Jeff", 201145, 0.016, 13, 0, 1, 4, 0.25, 1, 2, 0.5, 0, 2, 0.0], [201977, "Thornton, Marcus", "Boston Celtics", 1610612738, "BOS", "received", 48, "Rondo, Rajon", 200765, 0.091, 75, 10, 14, 31, 0.452, 7, 13, 0.538, 7, 18, 0.389], [201977, "Thornton, Marcus", "Boston Celtics", 1610612738, "BOS", "received", 48, "Bass, Brandon", 101138, 0.072, 59, 6, 12, 26, 0.462, 9, 19, 0.474, 3, 7, 0.429], [201977, "Thornton, Marcus", "Boston Celtics", 1610612738, "BOS", "received", 48, "Prince, Tayshaun", 2419, 0.029, 24, 2, 3, 11, 0.273, 2, 4, 0.5, 1, 7, 0.143], [201977, "Thornton, Marcus", "Boston Celtics", 1610612738, "BOS", "received", 48, "Wallace, Gerald", 2222, 0.012, 10, 0, 1, 5, 0.2, 1, 4, 0.25, 0, 1, 0.0], [201977, "Thornton, Marcus", "Phoenix Suns", 1610612756, "PHX", "received", 48, "Warren, T.J.", 203933, 0.005, 4, 1, 1, 2, 0.5, 0, 1, 0.0, 1, 1, 1.0], [201977, "Thornton, Marcus", "Phoenix Suns", 1610612756, "PHX", "received", 48, "Curry, Seth", 203552, 0.001, 1, 0, 0, 0, 0.0, 0, 0, 0.0, 0, 0, 0.0], [201977, "Thornton, Marcus", "Phoenix Suns", 1610612756, "PHX", "received", 48, "Bullock Jr., Reggie", 203493, 0.002, 2, 0, 0, 0, 0.0, 0, 0, 0.0, 0, 0, 0.0], [201977, "Thornton, Marcus", "Phoenix Suns", 1610612756, "PHX", "received", 48, "Goodwin, Archie", 203462, 0.016, 13, 1, 1, 5, 0.2, 0, 1, 0.0, 1, 4, 0.25], [201977, "Thornton, Marcus", "Phoenix Suns", 1610612756, "PHX", "received", 48, "Len, Alex", 203458, 0.004, 3, 0, 0, 2, 0.0, 0, 1, 0.0, 0, 1, 0.0], [201977, "Thornton, Marcus", "Phoenix Suns", 1610612756, "PHX", "received", 48, "Morris Sr., Marcus", 202694, 0.01, 8, 0, 0, 2, 0.0, 0, 0, 0.0, 0, 2, 0.0], [201977, "Thornton, Marcus", "Phoenix Suns", 1610612756, "PHX", "received", 48, "Morris, Markieff", 202693, 0.007, 6, 2, 2, 2, 1.0, 2, 2, 1.0, 0, 0, 0.0], [201977, "Thornton, Marcus", "Phoenix Suns", 1610612756, "PHX", "received", 48, "Knight, Brandon", 202688, 0.007, 6, 1, 1, 2, 0.5, 1, 2, 0.5, 0, 0, 0.0], [201977, "Thornton, Marcus", "Phoenix Suns", 1610612756, "PHX", "received", 48, "Bledsoe, Eric", 202339, 0.037, 30, 1, 2, 14, 0.143, 2, 7, 0.286, 0, 7, 0.0], [201977, "Thornton, Marcus", "Phoenix Suns", 1610612756, "PHX", "received", 48, "Wright, Brandan", 201148, 0.015, 12, 2, 2, 3, 0.667, 2, 2, 1.0, 0, 1, 0.0], [201977, "Thornton, Marcus", "Phoenix Suns", 1610612756, "PHX", "received", 48, "Tucker, P.J.", 200782, 0.011, 9, 0, 0, 3, 0.0, 0, 1, 0.0, 0, 2, 0.0], [201977, "Thornton, Marcus", "Phoenix Suns", 1610612756, "PHX", "received", 48, "Barron, Earl", 2853, 0.002, 2, 0, 1, 1, 1.0, 1, 1, 1.0, 0, 0, 0.0]]}]}