{"resource": "playerdashptpass", "parameters": {"PerMode": "Totals", "LeagueID": "00", "Season": "2024-25", "SeasonType": "Regular Season", "PlayerID": 1631243, "TeamID": 0, "Outcome": null, "Location": null, "Month": 0, "SeasonSegment": null, "DateFrom": null, "DateTo": null, "OpponentTeamID": 0, "VsConference": null, "VsDivision": null, "LastNGames": 0, "ISTRound": null}, "resultSets": [{"name": "PassesMade", "headers": ["PLAYER_ID", "PLAYER_NAME_LAST_FIRST", "TEAM_NAME", "TEAM_ID", "TEAM_ABBREVIATION", "PASS_TYPE", "G", "PASS_TO", "PASS_TEAMMATE_PLAYER_ID", "FREQUENCY", "PASS", "AST", "FGM", "FGA", "FG_PCT", "FG2M", "FG2A", "FG2_PCT", "FG3M", "FG3A", "FG3_PCT"], "rowSet": [[1631243, "Gueye, Mouhamed", "Atlanta Hawks", 1610612737, "ATL", "made", 33, "Risacher, Zaccharie", 1642258, 0.083, 36, 7, 7, 13, 0.538, 4, 7, 0.571, 3, 6, 0.5], [1631243, "Gueye, Mouhamed", "Atlanta Hawks", 1610612737, "ATL", "made", 33, "Plowden, Daeqwon", 1631342, 0.002, 1, 0, 0, 0, 0.0, 0, 0, 0.0, 0, 0, 0.0], [1631243, "Gueye, Mouhamed", "Atlanta Hawks", 1610612737, "ATL", "made", 33, "Barlow, Dominick", 1631230, 0.005, 2, 0, 0, 0, 0.0, 0, 0, 0.0, 0, 0, 0.0], [1631243, "Gueye, Mouhamed", "Atlanta Hawks", 1610612737, "ATL", "made", 33, "Roddy, David", 1631223, 0.005, 2, 0, 0, 0, 0.0, 0, 0, 0.0, 0, 0, 0.0], [1631243, "Gueye, Mouhamed", "Atlanta Hawks", 1610612737, "ATL", "made", 33, "Wallace, Keaton", 1630811, 0.083, 36, 0, 1, 4, 0.25, 1, 3, 0.333, 0, 1, 0.0], [1631243, "Gueye, Mouhamed", "Atlanta Hawks", 1610612737, "ATL", "made", 33, "Daniels, Dyson", 1630700, 0.171, 74, 3, 12, 17, 0.706, 11, 15, 0.733, 1, 2, 0.5], [1631243, "Gueye, Mouhamed", "Atlanta Hawks", 1610612737, "ATL", "made", 33, "Krej\u010d\u00ed, V\u00edt", 1630249, 0.074, 32, 2, 3, 5, 0.6, 2, 2, 1.0, 1, 3, 0.333], [1631243, "Gueye, Mouhamed", "Atlanta Hawks", 1610612737, "ATL", "made", 33, "Okongwu, Onyeka", 1630168, 0.06, 26, 5, 6, 12, 0.5, 3, 7, 0.429, 3, 5, 0.6], [1631243, "Gueye, Mouhamed", "Atlanta Hawks", 1610612737, "ATL", "made", 33, "Mathews, Garrison", 1629726, 0.007, 3, 0, 0, 0, 0.0, 0, 0, 0.0, 0, 0, 0.0], [1631243, "Gueye, Mouhamed", "Atlanta Hawks", 1610612737, "ATL", "made", 33, "Hunter, De'Andre", 1629631, 0.002, 1, 0, 0, 0, 0.0, 0, 0, 0.0, 0, 0, 0.0], [1631243, "Gueye, Mouhamed", "Atlanta Hawks", 1610612737, "ATL", "made", 33, "Mann, Terance", 1629611, 0.041, 18, 2, 6, 12, 0.5, 5, 8, 0.625, 1, 4, 0.25], [1631243, "Gueye, Mouhamed", "Atlanta Hawks", 1610612737, "ATL", "made", 33, "Young, Trae", 1629027, 0.415, 180, 3, 14, 43, 0.326, 9, 26, 0.346, 5, 17, 0.294], [1631243, "Gueye, Mouhamed", "Atlanta Hawks", 1610612737, "ATL", "made", 33, "Niang, Georges", 1627777, 0.009, 4, 0, 0, 3, 0.0, 0, 1, 0.0, 0, 2, 0.0], [1631243, "Gueye, Mouhamed", "Atlanta Hawks", 1610612737, "ATL", "made", 33, "LeVert, Caris", 1627747, 0.035, 15, 4, 5, 7, 0.714, 4, 6, 0.667, 1, 1, 1.0], [1631243, "Gueye, Mouhamed", "Atlanta Hawks", 1610612737, "ATL", "made", 33, "Nance Jr., Larry", 1626204, 0.005, 2, 0, 0, 2, 0.0, 0, 2, 0.0, 0, 0, 0.0], [1631243, "Gueye, Mouhamed", "Atlanta Hawks", 1610612737, "ATL", "made", 33, "Capela, Clint", 203991, 0.005, 2, 1, 1, 1, 1.0, 1, 1, 1.0, 0, 0, 0.0]]}, {"name": "PassesReceived", "headers": ["PLAYER_ID", "PLAYER_NAME_LAST_FIRST", "TEAM_NAME", "TEAM_ID", "TEAM_ABBREVIATION", "PASS_TYPE", "G", "PASS_FROM", "PASS_TEAMMATE_PLAYER_ID", "FREQUENCY", "PASS", "AST", "FGM", "FGA", "FG_PCT", "FG2M", "FG2A", "FG2_PCT", "FG3M", "FG3A", "FG3_PCT"], "rowSet": [[1631243, "Gueye, Mouhamed", "Atlanta Hawks", 1610612737, "ATL", "received", 33, "Risacher, Zaccharie", 1642258, 0.087, 30, 4, 4, 9, 0.444, 2, 2, 1.0, 2, 7, 0.286], [1631243, "Gueye, Mouhamed", "Atlanta Hawks", 1610612737, "ATL", "received", 33, "Plowden, Daeqwon", 1631342, 0.003, 1, 0, 0, 0, 0.0, 0, 0, 0.0, 0, 0, 0.0], [1631243, "Gueye, Mouhamed", "Atlanta Hawks", 1610612737, "ATL", "received", 33, "Barlow, Dominick", 1631230, 0.014, 5, 0, 0, 1, 0.0, 0, 1, 0.0, 0, 0, 0.0], [1631243, "Gueye, Mouhamed", "Atlanta Hawks", 1610612737, "ATL", "received", 33, "Roddy, David", 1631223, 0.009, 3, 0, 0, 1, 0.0, 0, 0, 0.0, 0, 1, 0.0], [1631243, "Gueye, Mouhamed", "Atlanta Hawks", 1610612737, "ATL", "received", 33, "Wallace, Keaton", 1630811, 0.066, 23, 2, 3, 8, 0.375, 2, 2, 1.0, 1, 6, 0.167], [1631243, "Gueye, Mouhamed", "Atlanta Hawks", 1610612737, "ATL", "received", 33, "Daniels, Dyson", 1630700, 0.185, 64, 10, 11, 29, 0.379, 7, 15, 0.467, 4, 14, 0.286], [1631243, "Gueye, Mouhamed", "Atlanta Hawks", 1610612737, "ATL", "received", 33, "Krej\u010d\u00ed, V\u00edt", 1630249, 0.052, 18, 3, 3, 6, 0.5, 2, 5, 0.4, 1, 1, 1.0], [1631243, "Gueye, Mouhamed", "Atlanta Hawks", 1610612737, "ATL", "received", 33, "Okongwu, Onyeka", 1630168, 0.11, 38, 12, 12, 18, 0.667, 7, 8, 0.875, 5, 10, 0.5], [1631243, "Gueye, Mouhamed", "Atlanta Hawks", 1610612737, "ATL", "received", 33, "Mathews, Garrison", 1629726, 0.023, 8, 1, 1, 3, 0.333, 1, 2, 0.5, 0, 1, 0.0], [1631243, "Gueye, Mouhamed", "Atlanta Hawks", 1610612737, "ATL", "received", 33, "Hunter, De'Andre", 1629631, 0.006, 2, 0, 0, 2, 0.0, 0, 0, 0.0, 0, 2, 0.0], [1631243, "Gueye, Mouhamed", "Atlanta Hawks", 1610612737, "ATL", "received", 33, "Mann, Terance", 1629611, 0.049, 17, 4, 4, 8, 0.5, 3, 4, 0.75, 1, 4, 0.25], [1631243, "Gueye, Mouhamed", "Atlanta Hawks", 1610612737, "ATL", "received", 33, "Young, Trae", 1629027, 0.329, 114, 21, 23, 66, 0.348, 18, 38, 0.474, 5, 28, 0.179], [1631243, "Gueye, Mouhamed", "Atlanta Hawks", 1610612737, "ATL", "received", 33, "Niang, Georges", 1627777, 0.009, 3, 0, 0, 3, 0.0, 0, 3, 0.0, 0, 0, 0.0], [1631243, "Gueye, Mouhamed", "Atlanta Hawks", 1610612737, "ATL", "received", 33, "LeVert, Caris", 1627747, 0.035, 12, 2, 2, 7, 0.286, 1, 3, 0.333, 1, 4, 0.25], [1631243, "Gueye, Mouhamed", "Atlanta Hawks", 1610612737, "ATL", "received", 33, "Nance Jr., Larry", 1626204, 0.02, 7, 3, 3, 6, 0.5, 2, 2, 1.0, 1, 4, 0.25], [1631243, "Gueye, Mouhamed", "Atlanta Hawks", 1610612737, "ATL", "received", 33, "Capela, Clint", 203991, 0.003, 1, 1, 1, 1, 1.0, 1, 1, 1.0, 0, 0, 0.0]]}]}